slack_beta_ti/__init__.py
slack_beta_ti/api_client.py
slack_beta_ti/api_response.py
slack_beta_ti/configuration.py
slack_beta_ti/exceptions.py
slack_beta_ti/py.typed
slack_beta_ti/rest.py
slack_beta_ti/api/__init__.py
slack_beta_ti/api/admin_api.py
slack_beta_ti/api/admin_apps_api.py
slack_beta_ti/api/admin_apps_approved_api.py
slack_beta_ti/api/admin_apps_requests_api.py
slack_beta_ti/api/admin_apps_restricted_api.py
slack_beta_ti/api/admin_conversations_api.py
slack_beta_ti/api/admin_conversations_ekm_api.py
slack_beta_ti/api/admin_conversations_restrict_access_api.py
slack_beta_ti/api/admin_emoji_api.py
slack_beta_ti/api/admin_invite_requests_api.py
slack_beta_ti/api/admin_invite_requests_approved_api.py
slack_beta_ti/api/admin_invite_requests_denied_api.py
slack_beta_ti/api/admin_teams_admins_api.py
slack_beta_ti/api/admin_teams_api.py
slack_beta_ti/api/admin_teams_owners_api.py
slack_beta_ti/api/admin_teams_settings_api.py
slack_beta_ti/api/admin_usergroups_api.py
slack_beta_ti/api/admin_users_api.py
slack_beta_ti/api/admin_users_session_api.py
slack_beta_ti/api/api_api.py
slack_beta_ti/api/apps_api.py
slack_beta_ti/api/apps_event_authorizations_api.py
slack_beta_ti/api/apps_permissions_api.py
slack_beta_ti/api/apps_permissions_resources_api.py
slack_beta_ti/api/apps_permissions_scopes_api.py
slack_beta_ti/api/apps_permissions_users_api.py
slack_beta_ti/api/auth_api.py
slack_beta_ti/api/bots_api.py
slack_beta_ti/api/calls_api.py
slack_beta_ti/api/calls_participants_api.py
slack_beta_ti/api/chat_api.py
slack_beta_ti/api/chat_scheduled_messages_api.py
slack_beta_ti/api/conversations_api.py
slack_beta_ti/api/dialog_api.py
slack_beta_ti/api/dnd_api.py
slack_beta_ti/api/emoji_api.py
slack_beta_ti/api/files_api.py
slack_beta_ti/api/files_comments_api.py
slack_beta_ti/api/files_remote_api.py
slack_beta_ti/api/migration_api.py
slack_beta_ti/api/oauth_api.py
slack_beta_ti/api/oauth_v2_api.py
slack_beta_ti/api/pins_api.py
slack_beta_ti/api/reactions_api.py
slack_beta_ti-0.0.1.dist-info/METADATA
slack_beta_ti-0.0.1.dist-info/WHEEL
slack_beta_ti-0.0.1.dist-info/top_level.txt
slack_beta_ti-0.0.1.dist-info/RECORD
